pypi_alias/__init__.py
pypi_alias/__main__.py
pypi_alias/cli.py
pypi_alias-2.0.0.dist-info/licenses/LICENSE
pypi_alias-2.0.0.dist-info/METADATA
pypi_alias-2.0.0.dist-info/WHEEL
pypi_alias-2.0.0.dist-info/entry_points.txt
pypi_alias-2.0.0.dist-info/top_level.txt
pypi_alias-2.0.0.dist-info/RECORD
