Metadata-Version: 2.4
Name: pypi-alias
Version: 2.0.0
Summary: A small utility to make alias distributions on PyPI.
Author-email: Ionel Cristian Mărieș <contact@ionelmc.ro>
License-Expression: BSD-2-Clause
Project-URL: Sources, https://github.com/ionelmc/pypi-alias
Project-URL: Changelog, https://github.com/ionelmc/pypi-alias/blob/master/CHANGELOG.rst
Project-URL: Issue Tracker, https://github.com/ionelmc/pypi-alias/issues
Classifier: Development Status :: 5 - Production/Stable
Classifier: Intended Audience :: Developers
Classifier: Operating System :: Unix
Classifier: Operating System :: POSIX
Classifier: Operating System :: Microsoft :: Windows
Classifier: Programming Language :: Python
Classifier: Programming Language :: Python :: 3
Classifier: Programming Language :: Python :: 3 :: Only
Classifier: Programming Language :: Python :: 3.9
Classifier: Programming Language :: Python :: 3.10
Classifier: Programming Language :: Python :: 3.11
Classifier: Programming Language :: Python :: 3.12
Classifier: Programming Language :: Python :: 3.13
Classifier: Programming Language :: Python :: Implementation :: CPython
Classifier: Programming Language :: Python :: Implementation :: PyPy
Classifier: Topic :: Utilities
Requires-Python: >=3.9
License-File: LICENSE
Requires-Dist: build
Requires-Dist: pkginfo
Dynamic: description
Dynamic: description-content-type
Dynamic: license-file
